structured_templates-0.1.1.dist-info/METADATA
structured_templates-0.1.1.dist-info/WHEEL
structured_templates-0.1.1.dist-info/entry_points.txt
structured_templates/__init__.py
structured_templates/context.py
structured_templates/engine.py
structured_templates/engine_test.py
structured_templates/exceptions.py
structured_templates/py.typed
structured_templates/types.py
structured_templates-0.1.1.dist-info/RECORD
