Metadata-Version: 2.1
Name: structured-templates
Version: 0.1.1
Summary: Templating engine for structured data (no free-form text generation).
Author-Email: Niklas Rosenstein <rosensteinniklas@gmail.com>
License: MIT
Requires-Python: >=3.10
